pypix_static/__init__.py
pypix_static/brcodes.py
pypix_static/utils/__init__.py
pypix_static-0.0.1.dist-info/LICENSE
pypix_static-0.0.1.dist-info/METADATA
pypix_static-0.0.1.dist-info/WHEEL
pypix_static-0.0.1.dist-info/top_level.txt
pypix_static-0.0.1.dist-info/RECORD
