Metadata-Version: 2.1
Name: pypix-static
Version: 0.0.1
Summary: Python library for generating Brazil's static PIX codes.
Home-page: https://github.com/feslima/pypix
Author: Felipe Souza Lima
Author-email: feslima93@gmail.com
License: UNKNOWN
Project-URL: Bug Tracker, https://github.com/feslima/pypix/issues
Platform: UNKNOWN
Classifier: Programming Language :: Python :: 3
Classifier: License :: OSI Approved :: MIT License
Classifier: Operating System :: OS Independent
Requires-Python: >=3.8
License-File: LICENSE
